django_redshift_backend/__init__.py
django_redshift_backend/base.py
django_redshift_backend/distkey.py
django_redshift_backend/meta.py
django_redshift_backend/psycopg2adapter.py
django_redshift_backend/_vendor/__init__.py
django_redshift_backend/_vendor/django40/__init__.py
django_redshift_backend/_vendor/django40/db/__init__.py
django_redshift_backend/_vendor/django40/db/backends/__init__.py
django_redshift_backend/_vendor/django40/db/backends/ddl_references.py
django_redshift_backend/_vendor/django40/db/backends/utils.py
django_redshift_backend/_vendor/django40/db/backends/base/__init__.py
django_redshift_backend/_vendor/django40/db/backends/base/base.py
django_redshift_backend/_vendor/django40/db/backends/base/client.py
django_redshift_backend/_vendor/django40/db/backends/base/creation.py
django_redshift_backend/_vendor/django40/db/backends/base/features.py
django_redshift_backend/_vendor/django40/db/backends/base/introspection.py
django_redshift_backend/_vendor/django40/db/backends/base/operations.py
django_redshift_backend/_vendor/django40/db/backends/base/schema.py
django_redshift_backend/_vendor/django40/db/backends/base/validation.py
django_redshift_backend/_vendor/django40/db/backends/postgresql/__init__.py
django_redshift_backend/_vendor/django40/db/backends/postgresql/base.py
django_redshift_backend/_vendor/django40/db/backends/postgresql/client.py
django_redshift_backend/_vendor/django40/db/backends/postgresql/creation.py
django_redshift_backend/_vendor/django40/db/backends/postgresql/features.py
django_redshift_backend/_vendor/django40/db/backends/postgresql/introspection.py
django_redshift_backend/_vendor/django40/db/backends/postgresql/operations.py
django_redshift_backend/_vendor/django40/db/backends/postgresql/schema.py
django_redshift_backend-5.0.0.dist-info/AUTHORS.rst
django_redshift_backend-5.0.0.dist-info/LICENSE
django_redshift_backend-5.0.0.dist-info/METADATA
django_redshift_backend-5.0.0.dist-info/WHEEL
django_redshift_backend-5.0.0.dist-info/top_level.txt
django_redshift_backend-5.0.0.dist-info/RECORD
