Metadata-Version: 2.1
Name: django-redshift-backend
Version: 5.0.0
Summary: Redshift database backend for Django
Author-email: shimizukawa <shimizukawa@gmail.com>
License:                                  Apache License
Project-URL: Documentation, https://django-redshift-backend.readthedocs.io/
Project-URL: Homepage, https://github.com/jazzband/django-redshift-backend
Project-URL: Release notes, https://django-redshift-backend.readthedocs.io/en/master/changes.html
Project-URL: Source, https://github.com/jazzband/django-redshift-backend
Project-URL: Tracker, https://github.com/jazzband/django-redshift-backend/issues
Keywords: django,redshift
Classifier: Development Status :: 5 - Production/Stable
Classifier: Environment :: Plugins
Classifier: Framework :: Django
Classifier: Framework :: Django :: 4.2
Classifier: Framework :: Django :: 5.0
Classifier: Framework :: Django :: 5.1
Classifier: Intended Audience :: Developers
Classifier: License :: OSI Approved :: Apache Software License
Classifier: Programming Language :: Python
Classifier: Programming Language :: Python :: 3
Classifier: Programming Language :: Python :: 3.9
Classifier: Programming Language :: Python :: 3.10
Classifier: Programming Language :: Python :: 3.11
Classifier: Programming Language :: Python :: 3.12
Classifier: Programming Language :: Python :: 3.13
Classifier: Topic :: Software Development :: Libraries :: Python Modules
Requires-Python: <4,>=3.9
License-File: LICENSE
License-File: AUTHORS.rst
Requires-Dist: django<5.2
Requires-Dist: backports.zoneinfo; python_version < "3.9"
Provides-Extra: psycopg2
Requires-Dist: psycopg2; extra == "psycopg2"
Provides-Extra: psycopg2-binary
Requires-Dist: psycopg2-binary; extra == "psycopg2-binary"
